modelOperationalization/__init__.py
modelOperationalization/cli.py
modelOperationalization/modelOperationalization.py
modelOperationalization-1.2.dist-info/DESCRIPTION.rst
modelOperationalization-1.2.dist-info/METADATA
modelOperationalization-1.2.dist-info/RECORD
modelOperationalization-1.2.dist-info/WHEEL
modelOperationalization-1.2.dist-info/metadata.json
modelOperationalization-1.2.dist-info/top_level.txt
