Metadata-Version: 2.0
Name: modelOperationalization
Version: 1.2
Summary: Project supporting serialization/deserliazation of Python objects
Home-page: https://github.scania.com/sssktw/modelOperationalization
Author: sssktw
Author-email: hany.kattow@scania.com
License: UNKNOWN
Requires-Dist: pyjo
